{
    "id": "Kiyoshi",
    "name": "Kiyoshi",
    "chapters": [
        {
            "title": "Chapter 24: Honey in the Tea",
            "info": "<a class='name' name='Kiyoshi'>Kiyoshi</a>, p. 526&#x2014;Aes Sedai of the Gray Ajah. <a href='#Alviarin'>Alviarin</a> commanded <a href='#Elaida'>Elaida</a> to uphold her as a model sister, and present her with the gift of a new horse. This came right after Elaida found <i>angreal</i> in the rooms of Josaine and <a href='#Adelorna'>Adelorna</a>; the obvious intent was to imply that Kiyoshi helped turn one of them in. It is unknown whether Kiyoshi is Black Ajah, or if she simply was chosen by Alviarin as a convenient person. She is tall, slender, and a stickler for punctuality and neatness. "
        }
    ]
}