{
    "id": "Birgitte",
    "name": "Birgitte",
    "chapters": [
        {
            "title": "Chapter 14: Meetings",
            "info": "<a class='name' name='Birgitte'>Birgitte</a>, p. 271 (193)&#x2014;A Hero of Legend bound to the Horn of Valere. She is an archer, and is always linked to <a href='#Gaidal'>Gaidal Cain</a> in the stories. She violates the precepts of <i>Tel&apos;aran&apos;rhiod</i> to help <a href='#Nynaeve'>Nynaeve</a> and <a href='#Elayne'>Elayne</a> fight the Shadow. She has blue eyes and golden hair, and carries a silver bow and silver arrows with which she never misses. Other than that, she is <i>nothing</i> like the stories of her. <i>See also</i> <a href='#Gaidal'>Cain, Gaidal</a>; <a href='#Maerion'>Maerion</a>. "
        }
    ]
}