{"id":"Chiad","name":"Chiad","chapters":[{"title":"Chapter 45:  A Bitter Thought","info":"<a class=\"name\" name=\"Chiad\">Chiad</a>,\n      p. 565 (793)&#x2014;A\n      Maiden of the Spear of the Stones River sept of the Goshien Aiel.  She\n      is short for an Aiel woman, and has blonde hair.\n      <a href=\"#Gaul\">Gaul</a> wants her to marry him, but she will not give\n      up the spear.  She is willing to be his lover, but marriage is out of\n      the question (or so she says).\n      <i>See also</i>\n      <a href=\"#Bain\">Bain</a>;\n      <a href=\"#Gaul\">Gaul</a>.\n  "}]}