{"id":"Taringail-Damodred","name":"Taringail Damodred","chapters":[{"title":"Chapter 6:  Surprises","info":"<a class=\"name\" name=\"Taringail\">Taringail Damodred</a>,\n      p. 110&#x2014;Cairhienin-born husband of the Queen of Andor.  He is\n      <a href=\"#Moiraine\">Moiraine</a>&apos;s half-brother.  He is denied the Sun\n      Throne of Cairhien due to his marriage to the Queen of Andor, leaving\n      very few choices for the Sun Throne in succession.\n      <i>See also</i>\n      <a href=\"#Aldecain\">Damodred, Aldecain</a>;\n      <a href=\"#Laman\">Damodred, Laman</a>;\n      <a href=\"#Moiraine\">Damodred, Moiraine</a>;\n      <a href=\"#Moressin\">Damodred, Moressin</a>.\n  "}]}