{"id":"Abell-Cauthon","name":"Abell Cauthon","chapters":[{"title":"Chapter 7:  Out of the Woods","info":"<a class=\"name\" name=\"Abell\">Abell Cauthon</a>,\n      p. 77&#x2014;<a href=\"#Mat\">Mat</a>&apos;s father.  His house was burned when the\n      Trollocs attacked Emond&apos;s Field on Winternight.\n      He has five children.\n      <i>See also</i>\n      <a href=\"#Bode\">Cauthon, Bodewhin</a>;\n      <a href=\"#Eldrin\">Cauthon, Eldrin</a>;\n      <a href=\"#Mat\">Cauthon, Matrim</a>;\n      <a href=\"#Natti\">Cauthon, Natti</a>.\n  "}]}