{
    "id": "Artur-Paendrag-Tanreall",
    "name": "Artur Paendrag Tanreall",
    "chapters": [
        {
            "title": "Chapter 4: The Gleeman",
            "info": "<a class='name' name='Artur'>Artur Paendrag Tanreall</a>, p. 43&#x2014;Hero of Legend who ruled all the lands from the Aiel Waste to the Aryth Ocean and beyond. He even sent troops across the Aryth Ocean, as well as to the lands beyond the Aiel Waste. His death set off the War of the Hundred Years. His sign was a golden hawk in flight; he was also known as <a href='#Hawkwing'>Artur Hawkwing</a>. "
        }
    ]
}