{"id":"Darl-Coplin","name":"Darl Coplin","chapters":[{"title":"Chapter 7: Out of the Woods","info":"<a class='name' name='Darl'>Darl Coplin</a>, p. 82&#x2014;Man from a farm near Emond&apos;s Field. He spent half the night demanding that <a href='#Bran'>Bran al&apos;Vere</a> send <a href='#Moiraine'>Moiraine</a> and <a href='#Lan'>Lan</a> away. He blamed them for bringing the Trollocs to Emond&apos;s Field. <i>See also</i> <a href='#Dag'>Coplin, Dag</a>; <a href='#Ewal'>Coplin, Ewal</a>; <a href='#Hari'>Coplin, Hari</a>. "}]}