{"id":"Andere","name":"Andere","chapters":[{"title":"Chapter 6:  A Knack","info":"<a class=\"name\" name=\"Andere\">Andere</a>,\n      p. 180&#x2014;Lean, dangerous-looking Malkieri man.  He spent most of his\n      life in Kandor, after Malkier fell.  He has long hair.  He started\n      wearing the <i>hadori</i> again recently.  <a href=\"#Lan\">Lan</a> has not seen\n      him in years&#x2014;he found Lan and company after word of Lan&apos;s march to\n      the Blight reached him.  He still fights at Lan&apos;s side.\n      <i>See also</i>\n      <a href=\"#Nazar\">Nazar</a>.\n  "}]}