{"id":"Car-a-carn","name":"Car'a'carn","chapters":[{"title":"Prologue: By Grace and Banners Fallen","info":"<i><a class='name' name='Caracarn'>Car&apos;a&apos;carn</a></i>, p. 43&#x2014;According to the Prophecy of Rhuidean, the man destined to unite the clans of the Aiel. The term means &#x201C;Chief of Chiefs&#x201D; in the Old Tongue. The <i>Car&apos;a&apos;carn</i>, according to the Prophecy, would be announced to the Aiel by not one, but <i>two</i> dragons on his forearms upon leaving Rhuidean. The <i>Car&apos;a&apos;carn</i> has arrived in the person of <a href='#Rand'>Rand al&apos;Thor</a>. <i>See also</i> <a href='#Rand'>al&apos;Thor, Rand</a>. "}]}