{
    "id": "Daerid",
    "name": "Daerid",
    "chapters": [
        {
            "title": "Chapter 41: A Smile",
            "info": "<a class='name' name='Daerid'>Daerid</a>, p. 834&#x2014;Former commander of the foot of the Band of the Red Hand. He is slightly taller than <a href='#Talmanes'>Talmanes</a>, and about fifteen years older. His nose has been broken many times. He has been a soldier all his life, and was not nobly born. He now is <a href='#Mat'>Mat</a>&apos;s dragoneer. "
        }
    ]
}