{
    "id": "Be-lal",
    "name": "Be'lal",
    "chapters": [
        {
            "title": "Prologue: Lightnings",
            "info": "<a class='name' name='Belal'>Be&apos;lal</a>, p. 40 (37)&#x2014;One of the Forsaken. After being released from the Bore, he took up residence in Tear as the High Lord Samon. He was killed by <a href='#Moiraine'>Moiraine</a> in the Stone of Tear, just before <a href='#Rand'>Rand</a> took <i>Callandor</i>. He had white hair at his temples, and was a Blademaster. Since he was destroyed by balefire, he is completely dead&#x2014;not even the <a href='#Dark'>Dark One</a> himself can bring him back. "
        }
    ]
}