{"id":"Queen-Tylin-Quintara-Mitsobar","name":"Queen Tylin Quintara Mitsobar","chapters":[{"title":"Prologue:  Lightnings","info":"<a class=\"name\" name=\"Tylin\">Queen Tylin Quintara Mitsobar</a>,\n      p. 18 (8)&#x2014;By the Grace of the Light, Queen of Altara, Mistress of the\n      Four Winds, Guardian of the Sea of Storms, High Seat of House Mitsobar.\n      Her kingdom is small, and she only rules a portion of it; the rest is\n      governed by nobles who are not necessarily loyal to her.  She is the\n      second from her House to sit on the throne&#x2014;this is the maximum\n      traditionally, and the only House to hold it for four generations fell\n      so fast from power that it could not recover.  She is advised by\n      <a href=\"#Merilille\">Merilille Ceandevin</a> of the Gray Ajah.  She is\n      a widow, and does not plan to marry again, although she is always on\n      the lookout for a lover....\n      <i>See also</i>\n      <a href=\"#Mat\">Cauthon, Matrim</a>;\n      <a href=\"#Beslan\">Mitsobar, Beslan</a>.\n  "}]}