{"id":"The-Empress-of-Seanchan-","name":"The Empress (of Seanchan)","chapters":[{"title":"Chapter 26:  The Irrevocable Words","info":"<a class=\"name\" name=\"Empress\">The Empress (of Seanchan)</a>,\n      p. 432 (552)&#x2014;Ruler of Seanchan.  She is considered to be a\n      direct descendant of the first emperor of Seanchan,\n      Luthair Paendrag Mondwhin.  She presides over the\n      Court of the Nine Moons on the Seanchan continent.\n      <i>See also</i>\n      <a href=\"#Artur\">Paendrag Tanreall, Artur</a>.\n  "}]}