{
    "id": "Doral-Barran",
    "name": "Doral Barran",
    "chapters": [
        {
            "title": "Chapter 30: What the Oath Rod Can Do",
            "info": "<a class='name' name='Doral'>Doral Barran</a>, p. 654 (791)&#x2014;Wisdom of Emond&apos;s Field years ago. When an epidemic of the spotted fever struck the city, she advocated holding brandy-soaked handkerchiefs over one&apos;s face to ward off the disease. Because of this, <a href='#Egwene'>Egwene</a> associated the smell of brandy with fear for a very long time. "
        }
    ]
}