{
    "id": "Osan-gar",
    "name": "Osan'gar",
    "chapters": [
        {
            "title": "Epilogue: An AnswerGlossary",
            "info": "<a class='name' name='Osangar'>Osan&apos;gar</a>, p. 690 (834)&#x2014;Name given to the reincarnation of one of the Forsaken. It was the left-hand dagger in a form of dueling popular right after the creation of the Bore. The sport fell from common practice, since almost invariably both duelists died from the slow poison on the daggers. Osan&apos;gar states that he helped make the Trollocs, indicating that in his past life he was Aginor. He spent months masquerading as Corlan Dashiva, one of the Asha&apos;man. Dashiva and Osan&apos;gar were killed at Shadar Logoth during the cleansing of <i>saidin</i>. <i>See also</i> <a href='#Arangar'>Aran&apos;gar</a>. "
        }
    ]
}