{"id":"Talene-Minly","name":"Talene Minly","chapters":[{"title":"Prologue:  Glimmers of the Pattern","info":"Talene Minly,\n      p. 44 (38)—Golden-haired Sitter for the Green Ajah in Tar Valon.  She used\n      to be Seaine's friend.  She has no Warders, which\n      is extremely unusual for a Green.  When Pevara\n      shielded her because she suspected her of being Black Ajah, she tried to\n      stab her.  She actually is a member of the Black Ajah, and is now\n      sworn to obey Pevara and Seaine unconditionally.  One of the three\n      other Black sisters she knew of was Atuan.\n      See also\n      Larisett, Atuan.\n  "}]}