{"id":"Brandelwyn-Bran-al-Vere","name":"Brandelwyn (Bran)  al'Vere","chapters":[{"title":"Chapter 29:  Homecoming","info":"<a class=\"name\" name=\"Bran\">Brandelwyn (Bran)  al&apos;Vere</a>,\n      p. 469 (421)&#x2014;Mayor of Emond&apos;s Field and owner of the\n      Winespring Inn.  He is <a href=\"#Marin\">Marin</a>&apos;s husband and\n      <a href=\"#Egwene\">Egwene</a>&apos;s father.  As mayor, he heads the Village\n      Council, and has to deal with the Wisdom should it be necessary to deal\n      with the Women&apos;s Circle.\n      <i>See also</i>\n      <a href=\"#Egwene\">al&apos;Vere, Egwene</a>;\n      <a href=\"#Marin\">al&apos;Vere, Marin</a>.\n  "}]}