{"id":"Haral-Luhhan","name":"Haral Luhhan","chapters":[{"title":"Chapter 2: Whirlpools in the Pattern","info":"<a class='name' name='Luhhan'>Haral Luhhan</a>, p. 57 (40)&#x2014;Blacksmith of Emond&apos;s Field. <a href='#Perrin'>Perrin</a> was his apprentice before he left home. He told Perrin that you cannot walk away from what has to be done&#x2014;Perrin heeds this advice. He is a very large man, which works well for work at the forge. His wife, <a href='#Alsbet'>Alsbet</a>, is almost as large as he is, and nearly as strong. <i>See also</i> <a href='#Alsbet'>Luhhan, Alsbet</a>. "}]}