{"id":"Moria-Elward","name":"Moria Elward","chapters":[{"title":"Chapter 17:  Deceptions","info":"<a class=\"name\" name=\"Elward\">Moria Elward</a>,\n      p. 292 (257)&#x2014;<a href=\"#Sahra\">Sahra Covenry</a>&apos;s taskmistress on the\n      penance farm.  She was not a harsh taskmistress, but Sahra did not come\n      to the White Tower to work on a farm.  She was killed by the same person\n      who killed Sahra.\n      <i>See also</i>\n      <a href=\"#Sahra\">Covenry, Sahra</a>.\n\n\n  "}]}