{"id":"Fergin","name":"Fergin","chapters":[{"title":"Chapter 9: Blood in the Air","info":"<a class='name' name='Fergin'>Fergin</a>, p. 161&#x2014;Bony Redarm. He is skinny, and a good soldier, but not very bright. He shares a tent with Harnan, Metwyn, and <a href='#Gorderan'>Gorderan</a>. He was killed when the <i>gholam</i> attacked Mat&apos;s camp. He and <a href='#Gorderan'>Gorderan</a> tried to use pikes against him, not realizing that the <i>gholam</i> could easily squeeze between them. "}]}