{
    "id": "Else-Grinwell",
    "name": "Else Grinwell",
    "chapters": [
        {
            "title": "Chapter 24: New Friends and Old Enemies",
            "info": "<a class='name' name='Else'>Else Grinwell</a>, p. 359 (316)&#x2014;Novice in the White Tower. <a href='#Elayne'>Elayne</a> describes her as a &#x201C;lazy chit.&#x201D; She was one of the people who allowed <a href='#Rand'>Rand</a> and <a href='#Mat'>Mat</a> to stay in her house (actually her parents&apos; house) while they were traveling from Emond&apos;s Field to Caemlyn on the way to Fal Dara. She is later dismissed from the Tower because of her habit of staring at the Warders&apos; students and not learning or doing her own work. "
        }
    ]
}