{"id":"Gaidal-Cain","name":"Gaidal Cain","chapters":[{"title":"Chapter 26:  Discord","info":"<a class=\"name\" name=\"Gaidal\">Gaidal Cain</a>,\n      p. 383 (337)&#x2014;Character out of legend who will be called back from the\n      dead by the Horn of Valere.\n      A swarthy man, he carries two swords and can use\n      them both from horseback.  He is always linked to\n      <a href=\"#Birgitte\">Birgitte</a> in the stories.\n      According to <a href=\"#Thom\">Thom</a>,\n      <a href=\"#Seaghan\">Seaghan</a> has hired a band of people to\n      impersonate such characters.\n      <i>See also</i>\n      <a href=\"#Birgitte\">Birgitte</a>.\n  "}]}