{"id":"Galadedrid-Galad-Damodred","name":"Galadedrid (Galad)  Damodred","chapters":[{"title":"Chapter 24:  New Friends and Old Enemies","info":"<a class=\"name\" name=\"Galad\">Galadedrid (Galad)  Damodred</a>,\n      p. 362 (318)&#x2014;Half-brother to\n      <a href=\"#Elayne\">Elayne</a> and <a href=\"#Gawyn\">Gawyn</a>, son\n      of their father <a href=\"#Taringail\">Taringail Damodred</a> and his\n      first wife, <a href=\"#Tigraine\">Tigraine</a>.  Galad always does what he\n      thinks is right, even if it would hurt his family and friends.  He has\n      extreme skill with a sword, learning everything the Warders teach\n      him after one demonstration.  He is strikingly handsome, even more\n      so than his half-brother Gawyn.  Like Gawyn, he has a crush\n      on <a href=\"#Egwene\">Egwene al&apos;Vere</a>, but she does not return\n      his feelings the way she does Gawyn&apos;s.\n      <i>See also</i>\n      <a href=\"#Taringail\">Damodred, Taringail</a>;\n      <a href=\"#Tigraine\">Damodred, Tigraine</a>;\n      <a href=\"#Elayne\">Trakand, Elayne</a>;\n      <a href=\"#Gawyn\">Trakand, Gawyn</a>;\n      <a href=\"#Morgase\">Trakand, Morgase</a>.\n\n\n  "}]}