{"id":"Lady-Amalisa-Jagad","name":"Lady Amalisa Jagad","chapters":[{"title":"Chapter 2: The Welcome","info":"<a class='name' name='Amalisa'>Lady Amalisa Jagad</a>, p. 13 (14)&#x2014;Sister of <a href='#Agelmar'>Lord Agelmar</a>. She is the one who actually delivers clothes to <a href='#Rand'>Rand</a>, <a href='#Mat'>Mat</a>, and <a href='#Perrin'>Perrin</a>. She is also the one who leads the search for the three boys when commanded by <a href='#Liandrin'>Liandrin</a>. She has a dark, mature beauty, and the color of her cheeks sets it off. <i>See also</i> <a href='#Agelmar'>Jagad, Agelmar</a>. "}]}