{
    "id": "Padan-Fain",
    "name": "Padan Fain",
    "chapters": [
        {
            "title": "Chapter 3: Friends and Enemies",
            "info": "<a class='name' name='Fain'>Padan Fain</a>, p. 39 (35)&#x2014;Former peddler, now found to be a Darkfriend. He can sense the presence of <a href='#Rand'>Rand al&apos;Thor</a> from a long distance, and has stolen the Horn of Valere. His scent, as described by the Sniffer <a href='#Hurin'>Hurin</a>, is worse than Trollocs, worse than Fades&#x2014;it is worse than evil. <i>See also</i> <a href='#Mordeth'>Mordeth</a>. "
        }
    ]
}