{
    "id": "Renna-Emain",
    "name": "Renna Emain",
    "chapters": [
        {
            "title": "Chapter 20: Questions of Treason",
            "info": "<a class='name' name='Renna'>Renna Emain</a>, p. 406 (466)&#x2014;<i>Sul&apos;dam</i> who was charged to train and control <a href='#Egwene'>Egwene</a> when she became a <i>damane</i>. She later gave her the nickname &#x201C;<a href='#Tuli'>Tuli</a>.&#x201D; When Egwene escaped, she put an <i>a&apos;dam</i> around Renna&apos;s neck, and left it there when she fled. Renna was later discovered by <a href='#Bethamin'>Bethamin</a>, wretching from the effort of removing the <i>a&apos;dam</i> in vain. To protect the Seanchan way of life&#x2014;which would likely collapse if it was learned that <i>sul&apos;dam</i> could learn to channel&#x2014;Renna retains her rank as <i>sul&apos;dam</i>, but is forbidden to be linked with a <i>damane</i>. She is kept under close watch by <a href='#Suroth'>Suroth</a>. "
        }
    ]
}