{"id":"Abell-Cauthon","name":"Abell Cauthon","chapters":[{"title":"Chapter 19: Awakening","info":"<a class='name' name='Abell'>Abell Cauthon</a>, p. 218 (172)&#x2014;<a href='#Mat'>Mat</a>&apos;s father. He is the best horse trader in the Two Rivers. He wins the quarterstaff competition at Bel Tine almost every year, and when he does not, <a href='#Tam'>Tam al&apos;Thor</a> does. He came to Tar Valon at one point to find out if Mat was still alive. <i>See also</i> <a href='#Mat'>Cauthon, Matrim</a>. "}]}